pyans
