Metadata-Version: 2.1
Name: pyans
Version: 0.1.3
Summary: Python Console ANSI viwer
Home-page: https://github.com/mtatton/pyans
Author: Michael Tatton
License: UNKNOWN
Platform: UNKNOWN
Classifier: Development Status :: 1 - Planning
Classifier: Intended Audience :: End Users/Desktop
Classifier: Topic :: Communications :: BBS
Classifier: Operating System :: POSIX :: Linux
Classifier: Programming Language :: Python :: 3.7
